Css3Jiaocheng/README.md
Css3Jiaocheng/__init__.py
Css3Jiaocheng/__main__.py
Css3Jiaocheng/file.epub
Css3Jiaocheng/index.html
Css3Jiaocheng/css/__init__.py
Css3Jiaocheng/css/annotations.css
Css3Jiaocheng/css/main.css
Css3Jiaocheng/css/normalize.css
Css3Jiaocheng/css/popup.css
Css3Jiaocheng/font/__init__.py
Css3Jiaocheng/font/fontello.eot
Css3Jiaocheng/font/fontello.svg
Css3Jiaocheng/font/fontello.ttf
Css3Jiaocheng/font/fontello.woff
Css3Jiaocheng/img/__init__.py
Css3Jiaocheng/img/annotator-glyph-sprite.png
Css3Jiaocheng/img/annotator-icon-sprite.png
Css3Jiaocheng/img/apple-touch-icon.png
Css3Jiaocheng/img/cancelfullscreen.png
Css3Jiaocheng/img/close.png
Css3Jiaocheng/img/fullscreen.png
Css3Jiaocheng/img/loader.gif
Css3Jiaocheng/img/menu-icon.png
Css3Jiaocheng/img/save.png
Css3Jiaocheng/img/saved.png
Css3Jiaocheng/img/settings-s.png
Css3Jiaocheng/img/settings.png
Css3Jiaocheng/img/star.png
Css3Jiaocheng/js/__init__.py
Css3Jiaocheng/js/epub.js
Css3Jiaocheng/js/epub.min.js
Css3Jiaocheng/js/epub.min.map
Css3Jiaocheng/js/hooks.min.js
Css3Jiaocheng/js/hooks.min.map
Css3Jiaocheng/js/reader.js
Css3Jiaocheng/js/reader.js.map
Css3Jiaocheng/js/reader.min.js
Css3Jiaocheng/js/reader.min.map
Css3Jiaocheng/js/hooks/__init__.py
Css3Jiaocheng/js/hooks/extensions/__init__.py
Css3Jiaocheng/js/hooks/extensions/highlight.js
Css3Jiaocheng/js/libs/__init__.py
Css3Jiaocheng/js/libs/jquery.min.js
Css3Jiaocheng/js/libs/localforage.min.js
Css3Jiaocheng/js/libs/screenfull.js
Css3Jiaocheng/js/libs/screenfull.min.js
Css3Jiaocheng/js/libs/zip.min.js
Css3Jiaocheng/js/plugins/__init__.py
Css3Jiaocheng/js/plugins/hypothesis.js
Css3Jiaocheng/js/plugins/search.js
css3_jiaocheng-2024.3.2.0.dist-info/METADATA
css3_jiaocheng-2024.3.2.0.dist-info/WHEEL
css3_jiaocheng-2024.3.2.0.dist-info/entry_points.txt
css3_jiaocheng-2024.3.2.0.dist-info/top_level.txt
css3_jiaocheng-2024.3.2.0.dist-info/RECORD
